{
  "assets": [
    {
      "id": "sprig-sentinel-idle",
      "file": "sprites/defenders/sprig-sentinel-idle.png",
      "sourceHash": "legacy-tree",
      "promptFile": "prompts/sprig-sentinel-idle.md",
      "references": ["assets/guardian.png", "docs/tower-defense-concept/art/towers-1.png"],
      "nativeSize": [256, 256],
      "drawSize": [82, 82],
      "anchor": [0.5, 0.82],
      "shadowRadius": 23,
      "tags": ["defender", "forest", "tier-1"],
      "fallback": "assets/tree.png"
    },
    {
      "id": "thornvine-bramble-idle",
      "file": "sprites/defenders/thornvine-bramble-idle.png",
      "promptFile": "prompts/thornvine-bramble-idle.md",
      "references": ["docs/tower-defense-concept/art/towers-1.png"],
      "nativeSize": [256, 256],
      "drawSize": [72, 72],
      "anchor": [0.5, 0.85],
      "shadowRadius": 20,
      "tags": ["defender", "forest", "blocker", "tier-1"]
    },
    {
      "id": "wisp-willow-idle",
      "file": "sprites/defenders/wisp-willow-idle.png",
      "promptFile": "prompts/wisp-willow-idle.md",
      "references": ["docs/tower-defense-concept/art/towers-1.png"],
      "nativeSize": [256, 256],
      "drawSize": [78, 78],
      "anchor": [0.5, 0.8],
      "shadowRadius": 22,
      "tags": ["defender", "arcane", "anti-air", "tier-1"]
    },
    {
      "id": "dewdrop-nymph-idle",
      "file": "sprites/defenders/dewdrop-nymph-idle.png",
      "promptFile": "prompts/dewdrop-nymph-idle.md",
      "references": ["docs/tower-defense-concept/art/towers-2.png"],
      "nativeSize": [256, 256],
      "drawSize": [76, 76],
      "anchor": [0.5, 0.82],
      "shadowRadius": 21,
      "tags": ["defender", "control", "tier-1"]
    },
    {
      "id": "firefly-beacon-idle",
      "file": "sprites/defenders/firefly-beacon-idle.png",
      "promptFile": "prompts/firefly-beacon-idle.md",
      "references": ["docs/tower-defense-concept/art/towers-1.png"],
      "nativeSize": [256, 256],
      "drawSize": [74, 74],
      "anchor": [0.5, 0.82],
      "shadowRadius": 20,
      "tags": ["defender", "support", "light", "tier-1"]
    },
    {
      "id": "mushroom-shaman-idle",
      "file": "sprites/defenders/mushroom-shaman-idle.png",
      "promptFile": "prompts/mushroom-shaman-idle.md",
      "references": ["docs/tower-defense-concept/art/towers-2.png"],
      "nativeSize": [256, 256],
      "drawSize": [78, 78],
      "anchor": [0.5, 0.82],
      "shadowRadius": 22,
      "tags": ["defender", "poison", "tier-1"]
    },
    {
      "id": "logger-idle",
      "file": "sprites/enemies/logger-idle.png",
      "promptFile": "prompts/logger-idle.md",
      "references": ["assets/logger.png", "docs/tower-defense-concept/art/enemies-1.png"],
      "nativeSize": [256, 256],
      "drawSize": [54, 68],
      "anchor": [0.5, 0.9],
      "shadowRadius": 18,
      "tags": ["enemy", "crew", "ground"],
      "fallback": "assets/logger.png"
    },
    {
      "id": "surveyor-idle",
      "file": "sprites/enemies/surveyor-idle.png",
      "promptFile": "prompts/surveyor-idle.md",
      "references": ["docs/tower-defense-concept/art/enemies-1.png"],
      "nativeSize": [256, 256],
      "drawSize": [50, 64],
      "anchor": [0.5, 0.9],
      "shadowRadius": 17,
      "tags": ["enemy", "crew", "ground"]
    },
    {
      "id": "chainsaw-brute-idle",
      "file": "sprites/enemies/chainsaw-brute-idle.png",
      "promptFile": "prompts/chainsaw-brute-idle.md",
      "references": ["docs/tower-defense-concept/art/enemies-1.png"],
      "nativeSize": [256, 256],
      "drawSize": [62, 72],
      "anchor": [0.5, 0.9],
      "shadowRadius": 20,
      "tags": ["enemy", "crew", "ground", "heavy"]
    },
    {
      "id": "bulldozer-idle",
      "file": "sprites/enemies/bulldozer-idle.png",
      "promptFile": "prompts/bulldozer-idle.md",
      "references": ["assets/dozer.png", "docs/tower-defense-concept/art/enemies-2.png"],
      "nativeSize": [256, 256],
      "drawSize": [78, 58],
      "anchor": [0.5, 0.88],
      "shadowRadius": 24,
      "tags": ["enemy", "machine", "ground"],
      "fallback": "assets/dozer.png"
    },
    {
      "id": "buzzsaw-drone-idle",
      "file": "sprites/enemies/buzzsaw-drone-idle.png",
      "promptFile": "prompts/buzzsaw-drone-idle.md",
      "references": ["docs/tower-defense-concept/art/enemies-2.png"],
      "nativeSize": [256, 256],
      "drawSize": [48, 48],
      "anchor": [0.5, 0.5],
      "shadowRadius": 16,
      "tags": ["enemy", "machine", "flying"]
    },
    {
      "id": "poacher-idle",
      "file": "sprites/enemies/poacher-idle.png",
      "promptFile": "prompts/poacher-idle.md",
      "references": ["docs/tower-defense-concept/art/enemies-1.png"],
      "nativeSize": [256, 256],
      "drawSize": [52, 66],
      "anchor": [0.5, 0.9],
      "shadowRadius": 18,
      "tags": ["enemy", "crew", "ground", "cloaked"]
    },
    {
      "id": "the-grinder-idle",
      "file": "sprites/enemies/the-grinder-idle.png",
      "promptFile": "prompts/the-grinder-idle.md",
      "references": ["docs/tower-defense-concept/art/enemies-2.png", "sprites/enemies/bulldozer-idle.png"],
      "nativeSize": [256, 256],
      "drawSize": [96, 80],
      "anchor": [0.5, 0.88],
      "shadowRadius": 28,
      "tags": ["enemy", "machine", "ground", "boss"]
    },
    {
      "id": "the-grinder-damaged",
      "file": "sprites/enemies/the-grinder-damaged.png",
      "promptFile": "prompts/the-grinder-damaged.md",
      "references": ["sprites/enemies/the-grinder-idle.png"],
      "nativeSize": [256, 256],
      "drawSize": [96, 80],
      "anchor": [0.5, 0.88],
      "shadowRadius": 28,
      "tags": ["enemy", "machine", "ground", "boss"]
    },
    {
      "id": "material-grass",
      "file": "materials/grass-tile.png",
      "promptFile": "prompts/material-grass.md",
      "references": ["docs/tower-defense-concept/art/gameplay-mockup.png"],
      "nativeSize": [128, 128],
      "drawSize": [128, 128],
      "anchor": [0, 0],
      "tags": ["material", "tileable", "meadow-edge"]
    },
    {
      "id": "material-mushroom-floor",
      "file": "materials/mushroom-floor.png",
      "promptFile": "prompts/material-mushroom-floor.md",
      "references": ["docs/tower-defense-concept/art/gameplay-mockup.png"],
      "nativeSize": [128, 128],
      "drawSize": [128, 128],
      "anchor": [0, 0],
      "tags": ["material", "tileable", "mushroom-hollow"]
    },
    {
      "id": "material-sawmill-floor",
      "file": "materials/sawmill-floor.png",
      "promptFile": "prompts/material-sawmill-floor.md",
      "references": ["docs/tower-defense-concept/art/gameplay-mockup.png"],
      "nativeSize": [128, 128],
      "drawSize": [128, 128],
      "anchor": [0, 0],
      "tags": ["material", "tileable", "sawmill"]
    },
    {
      "id": "material-path-interior",
      "file": "materials/path-interior.png",
      "promptFile": "prompts/material-path-interior.md",
      "references": ["docs/tower-defense-concept/art/gameplay-mockup.png"],
      "nativeSize": [128, 128],
      "drawSize": [128, 128],
      "anchor": [0, 0],
      "tags": ["material", "tileable", "path"]
    },
    {
      "id": "decoration-stump",
      "file": "decorations/stump.png",
      "promptFile": "prompts/decoration-stump.md",
      "references": ["docs/tower-defense-concept/art/gameplay-mockup.png"],
      "nativeSize": [128, 128],
      "drawSize": [48, 48],
      "anchor": [0.5, 0.85],
      "tags": ["decoration", "stump-crossroads"]
    },
    {
      "id": "landmark-broken-fence",
      "file": "decorations/broken-fence.png",
      "promptFile": "prompts/landmark-broken-fence.md",
      "references": ["docs/tower-defense-concept/art/gameplay-mockup.png"],
      "nativeSize": [256, 256],
      "drawSize": [80, 80],
      "anchor": [0.5, 0.9],
      "tags": ["landmark", "meadow-edge"]
    },
    {
      "id": "landmark-glow-mushroom",
      "file": "decorations/glow-mushroom-cluster.png",
      "promptFile": "prompts/landmark-glow-mushroom.md",
      "references": ["docs/tower-defense-concept/art/gameplay-mockup.png"],
      "nativeSize": [256, 256],
      "drawSize": [88, 88],
      "anchor": [0.5, 0.88],
      "tags": ["landmark", "mushroom-hollow", "light"]
    },
    {
      "id": "landmark-sawmill-debris",
      "file": "decorations/sawmill-debris.png",
      "promptFile": "prompts/landmark-sawmill-debris.md",
      "references": ["decorations/broken-fence.png"],
      "nativeSize": [256, 256],
      "drawSize": [92, 92],
      "anchor": [0.5, 0.9],
      "tags": ["landmark", "sawmill"]
    }
  ]
}
